DBUtils/PersistentDB.py
DBUtils/PersistentPg.py
DBUtils/PooledDB.py
DBUtils/PooledPg.py
DBUtils/Properties.py
DBUtils/SimplePooledDB.py
DBUtils/SimplePooledPg.py
DBUtils/SteadyDB.py
DBUtils/SteadyPg.py
DBUtils/ThreadingLocal.py
DBUtils/__init__.py
DBUtils/Examples/DBUtilsExample.py
DBUtils/Examples/Main.py
DBUtils/Examples/__init__.py
DBUtils/Tests/TestPersistentDB.py
DBUtils/Tests/TestPersistentPg.py
DBUtils/Tests/TestPooledDB.py
DBUtils/Tests/TestPooledPg.py
DBUtils/Tests/TestSimplePooledDB.py
DBUtils/Tests/TestSimplePooledPg.py
DBUtils/Tests/TestSteadyDB.py
DBUtils/Tests/TestSteadyPg.py
DBUtils/Tests/TestThreadingLocal.py
DBUtils/Tests/__init__.py
databricks_s3_mount/__init__.py
databricks_s3_mount/mount.py
databricks_s3_mount-1.2.dist-info/METADATA
databricks_s3_mount-1.2.dist-info/WHEEL
databricks_s3_mount-1.2.dist-info/top_level.txt
databricks_s3_mount-1.2.dist-info/RECORD
