Metadata-Version: 2.1
Name: databricks-s3-mount
Version: 1.2
Summary: databricks s3 mount with assumed role
Home-page: UNKNOWN
Author: BOS TEAM
Author-email: bos-tribe@ReedElsevier.com
License: UNKNOWN
Platform: UNKNOWN
